README.md
setup.py
topsis/__init__.py
topsis/topsis.py
topsis_sachingoyal_102303557.egg-info/PKG-INFO
topsis_sachingoyal_102303557.egg-info/SOURCES.txt
topsis_sachingoyal_102303557.egg-info/dependency_links.txt
topsis_sachingoyal_102303557.egg-info/entry_points.txt
topsis_sachingoyal_102303557.egg-info/requires.txt
topsis_sachingoyal_102303557.egg-info/top_level.txt